jinja2_shell_extension/__init__.py
jinja2_shell_extension-2.1.1.dist-info/licenses/LICENSE
jinja2_shell_extension-2.1.1.dist-info/METADATA
jinja2_shell_extension-2.1.1.dist-info/WHEEL
jinja2_shell_extension-2.1.1.dist-info/top_level.txt
jinja2_shell_extension-2.1.1.dist-info/RECORD
