Metadata-Version: 2.4
Name: jinja2_shell_extension
Version: 2.1.1
Summary: a jinja2 extension to access to system environment variables
Home-page: https://github.com/metwork-framework/jinja2_shell_extension
Author: Fabien MARTY
Author-email: fabien.marty@gmail.com
License: BSD
Keywords: jinja2 extension
Classifier: Development Status :: 5 - Production/Stable
Classifier: Intended Audience :: Developers
Classifier: Programming Language :: Python :: 3
Requires-Python: >=3.0
License-File: LICENSE
Requires-Dist: jinja2
Dynamic: author
Dynamic: author-email
Dynamic: classifier
Dynamic: description
Dynamic: description-content-type
Dynamic: home-page
Dynamic: keywords
Dynamic: license
Dynamic: license-file
Dynamic: requires-dist
Dynamic: requires-python
Dynamic: summary
